forcedimension_core/__init__.py
forcedimension_core/constants.py
forcedimension_core/containers/__init__.py
forcedimension_core/containers/numpy.py
forcedimension_core/deprecated/__init__.py
forcedimension_core/deprecated/constants.py
forcedimension_core/dhd/__init__.py
forcedimension_core/dhd/adaptors.py
forcedimension_core/dhd/direct.py
forcedimension_core/dhd/expert/__init__.py
forcedimension_core/dhd/expert/direct.py
forcedimension_core/dhd/os_independent.py
forcedimension_core/drd/__init__.py
forcedimension_core/drd/adaptors.py
forcedimension_core/drd/direct.py
forcedimension_core/runtime.py
forcedimension_core/typing.py
forcedimension_core/util.py
forcedimension_core-1.0.0.dist-info/LICENSE
forcedimension_core-1.0.0.dist-info/METADATA
forcedimension_core-1.0.0.dist-info/WHEEL
forcedimension_core-1.0.0.dist-info/RECORD
