Metadata-Version: 2.1
Name: forcedimension-core
Version: 1.0.0
Summary: Unofficial Python Bindings for the Force Dimension SDK
Home-page: https://github.com/EmDash00/forcedimension_core-python
License: LGPL-3.0
Keywords: forcedimension,haptics,bindings
Author: Ember Chow
Author-email: emberchow.business@gmail.com
Requires-Python: >=3.8,<3.13
Classifier: Development Status :: 5 - Production/Stable
Classifier: License :: OSI Approved :: GNU Lesser General Public License v3 (LGPLv3)
Classifier: Operating System :: MacOS :: MacOS X
Classifier: Operating System :: Microsoft :: Windows
Classifier: Operating System :: POSIX :: Linux
Classifier: Programming Language :: Python :: 3
Classifier: Programming Language :: Python :: 3.8
Classifier: Programming Language :: Python :: 3.9
Classifier: Programming Language :: Python :: 3.10
Classifier: Programming Language :: Python :: 3.11
Classifier: Programming Language :: Python :: 3.12
Classifier: Programming Language :: Python :: Implementation :: CPython
Classifier: Programming Language :: Python :: Implementation :: PyPy
Classifier: Topic :: System :: Hardware :: Universal Serial Bus (USB) :: Human Interface Device (HID)
Provides-Extra: numpy
Requires-Dist: numpy (>=1.20.0,<2.0.0) ; (python_version < "3.12") and (extra == "numpy")
Requires-Dist: numpy (>=1.26.0,<2.0.0) ; (python_version >= "3.12" and python_version < "3.13") and (extra == "numpy")
Requires-Dist: pydantic (>=2,<3)
Requires-Dist: typing-extensions (>=4.6.0,<5.0.0)
Project-URL: Changelog, https://github.com/EmDash00/forcedimension_core-python/blob/main/CHANGELOG.md
Project-URL: Documentation, https://forcedimension-core-python-docs.readthedocs.io/en/v1.0.0/
Project-URL: Repository, https://github.com/EmDash00/forcedimension_core-python
